prepsaa/__init__.py
prepsaa/cli.py
prepsaa/constants.py
prepsaa/models.py
prepsaa/services.py
prepsaa/settings.py
prepsaa/utils.py
prepsaa-0.1.3.dist-info/METADATA
prepsaa-0.1.3.dist-info/WHEEL
prepsaa-0.1.3.dist-info/entry_points.txt
prepsaa-0.1.3.dist-info/licenses/LICENSE
prepsaa-0.1.3.dist-info/RECORD
