Metadata-Version: 2.4
Name: prepsaa
Version: 0.1.3
Summary: AWS SAA 시험 대비를 위한 LLM 기반 CLI 도구
License-File: LICENSE
Requires-Python: >=3.12
Requires-Dist: langchain-anthropic>=0.3.12
Requires-Dist: langchain-google-genai>=2.1.4
Requires-Dist: langchain-openai>=0.3.16
Requires-Dist: langchain>=0.3.25
Requires-Dist: notion-client>=2.3.0
Requires-Dist: notionize>=0.2.3
Requires-Dist: pydantic-settings>=2.9.1
Requires-Dist: tenacity>=9.1.2
Requires-Dist: typer>=0.15.3
